.coveragerc
.hgignore
.hgsub
.hgsubstate
.hgtags
CHANGES.txt
COPYRIGHT.txt
HACKING.txt
LICENSE.txt
Makefile
README.txt
bootstrap.py
buildout.cfg
setup.py
src/ajja/__init__.py
src/ajja/resource.py
src/ajja.egg-info/PKG-INFO
src/ajja.egg-info/SOURCES.txt
src/ajja.egg-info/dependency_links.txt
src/ajja.egg-info/entry_points.txt
src/ajja.egg-info/not-zip-safe
src/ajja.egg-info/requires.txt
src/ajja.egg-info/top_level.txt
src/ajja/additional/handlebars-v4.0.2.js
src/ajja/additional/handlebars-v4.0.2.min.js
src/ajja/additional/ko.mapping.js
src/ajja/additional/ko.mapping.min.js
src/ajja/resources/bower.json
src/ajja/resources/collection.js
src/ajja/resources/collection.min.js
src/ajja/resources/form.js
src/ajja/resources/form.min.js
src/ajja/resources/helpers.js
src/ajja/resources/helpers.min.js
src/ajja/resources/localizations
src/ajja/resources/template.js
src/ajja/resources/template.min.js
src/ajja/resources/templates.js
src/ajja/resources/templates.min.js
src/ajja/tests/__init__.py
src/ajja/tests/test_integration.py
src/ajja/tests/test_minification.py
src/ajja/tests/resources/groupwidget.js
src/ajja/tests/resources/jsform.js
src/ajja/tests/resources/listwidget.js
src/ajja/tests/resources/tablewidget.js
src/ajja/tests/resources/testdata.json
versions/versions.cfg
versions/ztk-versions-1.1.5.cfg