Metadata-Version: 1.1
Name: ajja
Version: 4.0.0
Summary: Next generation forms in javascript
Home-page: https://github.com/gocept/ajja
Author: Sebastian Wehrmann <sw@gocept.com>, Maik Derstappen <md@derico.de>
Author-email: sw@gocept.com
License: MIT
Keywords: form javascript jquery client
Platform: UNKNOWN
Classifier: License :: OSI Approved :: MIT License
Classifier: Programming Language :: Python
Classifier: Programming Language :: Python :: 2
Classifier: Programming Language :: Python :: 2.6
Classifier: Programming Language :: Python :: 2.7
Classifier: Programming Language :: Python :: 2 :: Only
